gisansexplorer/GUI.py
gisansexplorer/__init__.py
gisansexplorer/__main__.py
gisansexplorer/experiment_data_handling.py
gisansexplorer/main_app.py
gisansexplorer/plotting.py
gisansexplorer/utils.py
gisansexplorer-1.0.0.data/data/resources/Icon.png
gisansexplorer-1.0.0.data/data/resources/show_test_map.npy
gisansexplorer-1.0.0.dist-info/LICENSE
gisansexplorer-1.0.0.dist-info/METADATA
gisansexplorer-1.0.0.dist-info/WHEEL
gisansexplorer-1.0.0.dist-info/entry_points.txt
gisansexplorer-1.0.0.dist-info/top_level.txt
gisansexplorer-1.0.0.dist-info/RECORD
