Metadata-Version: 2.1
Name: gisansexplorer
Version: 1.0.0
Summary: Nicos data reduction and visualisation tool
Home-page: https://github.com/juanmcloaiza/gisansexplorer
Author: Juan M. Carmona Loaiza
Author-email: j.carmona.loaiza@fz-juelich.de
License: UNKNOWN
Platform: UNKNOWN
Classifier: Programming Language :: Python :: 3
Classifier: Operating System :: OS Independent
Requires-Python: >=3.6
